_ulog/__init__.py
arsdk/antenna.proto
arsdk/antiflicker.proto
arsdk/camera2.proto
arsdk/camera_alert.proto
arsdk/connectivity.proto
arsdk/controller_network.proto
arsdk/controller_privacy.proto
arsdk/developer.proto
arsdk/device_manager.proto
arsdk/killswitch.proto
arsdk/led.proto
arsdk/microhard.proto
arsdk/netdebuglog.proto
arsdk/network.proto
arsdk/pointnfly.proto
arsdk/privacy.proto
arsdk/security.proto
arsdk/sleepmode.proto
arsdk/sms.proto
arsdk/xml/alarms.xml
arsdk/xml/animation.xml
arsdk/xml/ardrone3.xml
arsdk/xml/auto_look_at.xml
arsdk/xml/battery.xml
arsdk/xml/camera.xml
arsdk/xml/cellular.xml
arsdk/xml/common.xml
arsdk/xml/controller_info.xml
arsdk/xml/debug.xml
arsdk/xml/dri.xml
arsdk/xml/drone_manager.xml
arsdk/xml/fcr.xml
arsdk/xml/flight_plan.xml
arsdk/xml/followme.xml
arsdk/xml/gauge_fw_updater.xml
arsdk/xml/generic.xml
arsdk/xml/gimbal.xml
arsdk/xml/hand_land.xml
arsdk/xml/leds.xml
arsdk/xml/mapper.xml
arsdk/xml/mapper_mini.xml
arsdk/xml/mediastore.xml
arsdk/xml/mission.xml
arsdk/xml/motors.xml
arsdk/xml/move.xml
arsdk/xml/obstacle_avoidance.xml
arsdk/xml/onboard_tracker.xml
arsdk/xml/piloting_style.xml
arsdk/xml/poi.xml
arsdk/xml/powerup.xml
arsdk/xml/precise_home.xml
arsdk/xml/rc.xml
arsdk/xml/rc_transport.xml
arsdk/xml/rth.xml
arsdk/xml/security_edition.xml
arsdk/xml/sequoia.xml
arsdk/xml/skyctrl.xml
arsdk/xml/stereo_vision_sensor.xml
arsdk/xml/terrain.xml
arsdk/xml/thermal.xml
arsdk/xml/thermal_cam.xml
arsdk/xml/user_storage.xml
arsdk/xml/user_storage_v2.xml
arsdk/xml/wifi.xml
arsdkparser.py
logness/__init__.py
olympe/.flake8
olympe/__init__.py
olympe/__version__.py
olympe/app.py
olympe/arsdkng/__init__.py
olympe/arsdkng/backend.py
olympe/arsdkng/cmd_itf.py
olympe/arsdkng/controller.py
olympe/arsdkng/device.py
olympe/arsdkng/discovery.py
olympe/arsdkng/enums.py
olympe/arsdkng/events.py
olympe/arsdkng/expectations.py
olympe/arsdkng/json.py
olympe/arsdkng/messages.py
olympe/arsdkng/proto.py
olympe/arsdkng/proto_this.py
olympe/arsdkng/xml.py
parrot_olympe-7.7.4.dist-info/LICENSE.txt
parrot_olympe-7.7.4.dist-info/METADATA
parrot_olympe-7.7.4.dist-info/WHEEL
parrot_olympe-7.7.4.dist-info/entry_points.txt
parrot_olympe-7.7.4.dist-info/RECORD
