Metadata-Version: 2.1
Name: parrot-olympe
Version: 7.7.4
Summary: Python controller library for Parrot Drones
Keywords: uav,parrot,drones,parrot-drones
Home-page: https://developer.parrot.com/
Author: Nicolas Dessart
License: BSD 3-Clause Modification
Classifier: Development Status :: 4 - Beta
Classifier: Intended Audience :: Developers
Classifier: Intended Audience :: Education
Classifier: Intended Audience :: Science/Research
Classifier: License :: OSI Approved :: BSD License
Classifier: License :: OSI Approved
Classifier: Operating System :: POSIX :: Linux
Classifier: Programming Language :: C
Classifier: Programming Language :: Python :: 3.6
Classifier: Programming Language :: Python :: 3.7
Classifier: Programming Language :: Python :: 3.8
Classifier: Programming Language :: Python :: 3.9
Classifier: Programming Language :: Python
Classifier: Topic :: Scientific/Engineering :: Artificial Intelligence
Classifier: Topic :: Scientific/Engineering :: Image Processing
Classifier: Topic :: Scientific/Engineering
Requires-Dist: aenum
Requires-Dist: asn1tools
Requires-Dist: black
Requires-Dist: boltons
Requires-Dist: colorlog
Requires-Dist: dacite
Requires-Dist: dataclasses; python_version == '3.6'
Requires-Dist: future
Requires-Dist: geopy
Requires-Dist: h11
Requires-Dist: ipython
Requires-Dist: importlib_metadata; python_version < '3.8'
Requires-Dist: numpy
Requires-Dist: typing-protocol; python_version < '3.8'
Requires-Dist: protobuf==3.19.4
Requires-Dist: pycryptodomex
Requires-Dist: pytz
Requires-Dist: PyYAML
Requires-Dist: requests
Requires-Dist: six
Requires-Dist: tzlocal<4.0
Requires-Dist: wsproto
Requires-Dist: PyOpenGL; extra == 'rendering'
Requires-Dist: PyOpenGL-accelerate; extra == 'rendering'
Requires-Dist: PySDL2; extra == 'rendering'
Requires-Dist: Sphinx; extra == 'doc'
Requires-Dist: blockdiag; extra == 'doc'
Requires-Dist: furo; extra == 'doc'
Requires-Dist: seqdiag; extra == 'doc'
Requires-Dist: sphinx-copybutton; extra == 'doc'
Requires-Dist: sphinxcontrib-seqdiag; extra == 'doc'
Requires-Dist: pytest; extra == 'tests'
Requires-Python: >=3.6
Project-URL: documentation, https://developer.parrot.com/docs/olympe/
Project-URL: repository, https://github.com/Parrot-Developers/olympe
Provides-Extra: rendering
Provides-Extra: doc
Provides-Extra: tests
